{
  "jeg:recipes/jeg/workbench": {
    "criteria": {
      "has_planks": "2024-11-30 18:32:36 +0300"
    },
    "done": true
  },
  "smallships:recipes/transportation/birch_drakkar": {
    "criteria": {
      "in_water": "2024-11-29 21:57:35 +0300"
    },
    "done": true
  },
  "mcwfences:recipes/deepslate": {
    "criteria": {
      "has_deepslate": "2024-11-29 21:36:38 +0300"
    },
    "done": true
  },
  "smallships:recipes/transportation/jungle_drakkar": {
    "criteria": {
      "in_water": "2024-11-29 21:57:34 +0300"
    },
    "done": true
  },
  "smallships:recipes/transportation/acacia_cog": {
    "criteria": {
      "in_water": "2024-11-29 21:57:34 +0300"
    },
    "done": true
  },
  "mcwbridges:recipes/oak_log_bridge_middle": {
    "criteria": {
      "has_planks": "2024-11-30 18:32:36 +0300"
    },
    "done": true
  },
  "mcwwindows:recipes/blinds": {
    "criteria": {
      "has_wood": "2024-11-30 18:32:36 +0300",
      "has_the_recipe": "2024-11-30 18:32:36 +0300"
    },
    "done": true
  },
  "mcwfences:recipes/sandstone": {
    "criteria": {
      "has_sand": "2024-11-29 21:36:38 +0300"
    },
    "done": true
  },
  "minecraft:recipes/decorations/crafting_table": {
    "criteria": {
      "has_planks": "2024-11-30 18:32:36 +0300"
    },
    "done": true
  },
  "mcwfences:recipes/mud_brick": {
    "criteria": {
      "has_qq": "2024-11-29 21:36:38 +0300"
    },
    "done": true
  },
  "smallships:recipes/transportation/birch_cog": {
    "criteria": {
      "in_water": "2024-11-29 21:57:34 +0300"
    },
    "done": true
  },
  "mcwbridges:recipes/asian_red_bridge": {
    "criteria": {
      "has_planks": "2024-11-30 18:32:36 +0300"
    },
    "done": true
  },
  "smallships:recipes/transportation/spruce_drakkar": {
    "criteria": {
      "in_water": "2024-11-29 21:57:35 +0300"
    },
    "done": true
  },
  "smallships:recipes/transportation/oak_cog": {
    "criteria": {
      "in_water": "2024-11-29 21:57:34 +0300"
    },
    "done": true
  },
  "minecraft:recipes/transportation/mangrove_boat": {
    "criteria": {
      "in_water": "2024-11-29 21:57:35 +0300"
    },
    "done": true
  },
  "cfm:recipes/cfm/oak_chair": {
    "criteria": {
      "has_planks": "2024-11-30 18:32:36 +0300"
    },
    "done": true
  },
  "mcwtrpdoors:recipes/oak_blossom_trapdoor": {
    "criteria": {
      "has_plankss": "2024-11-30 18:32:36 +0300"
    },
    "done": true
  },
  "mcwfences:recipes/stone": {
    "criteria": {
      "has_stone": "2024-11-29 21:36:38 +0300"
    },
    "done": true
  },
  "mcwfences:recipes/mangrove": {
    "criteria": {
      "has_mangrove": "2024-11-29 21:36:38 +0300"
    },
    "done": true
  },
  "cfm:recipes/cfm/oak_crate": {
    "criteria": {
      "has_planks": "2024-11-30 18:32:36 +0300"
    },
    "done": true
  },
  "mcwfences:recipes/warped": {
    "criteria": {
      "has_warped": "2024-11-29 21:36:38 +0300"
    },
    "done": true
  },
  "minecraft:recipes/misc/stick": {
    "criteria": {
      "has_planks": "2024-11-30 18:32:36 +0300"
    },
    "done": true
  },
  "smallships:recipes/transportation/acacia_galley": {
    "criteria": {
      "in_water": "2024-11-29 21:57:35 +0300"
    },
    "done": true
  },
  "minecraft:recipes/transportation/spruce_boat": {
    "criteria": {
      "in_water": "2024-11-29 21:57:35 +0300"
    },
    "done": true
  },
  "create:recipes/create.palettes/oak_window": {
    "criteria": {
      "has_ingredient": "2024-11-30 18:32:36 +0300"
    },
    "done": true
  },
  "smallships:recipes/transportation/mangrove_cog": {
    "criteria": {
      "in_water": "2024-11-29 21:57:35 +0300"
    },
    "done": true
  },
  "mcwfences:recipes/jungle": {
    "criteria": {
      "has_jungle": "2024-11-29 21:36:38 +0300"
    },
    "done": true
  },
  "cfm:recipes/cfm/oak_kitchen_counter": {
    "criteria": {
      "has_planks": "2024-11-30 18:32:36 +0300"
    },
    "done": true
  },
  "mcwroofs:recipes/oak_planks": {
    "criteria": {
      "has_planks": "2024-11-30 18:32:36 +0300"
    },
    "done": true
  },
  "mcwfences:recipes/spruce": {
    "criteria": {
      "has_spruce": "2024-11-29 21:36:38 +0300"
    },
    "done": true
  },
  "mcwfences:recipes/oak": {
    "criteria": {
      "has_oak": "2024-11-29 21:36:38 +0300"
    },
    "done": true
  },
  "mcwfences:recipes/hedge": {
    "criteria": {
      "has_birch": "2024-11-29 21:36:38 +0300"
    },
    "done": true
  },
  "mcwfences:recipes/end": {
    "criteria": {
      "has_end_brick": "2024-11-29 21:36:38 +0300"
    },
    "done": true
  },
  "createdeco:recipes/createdeco.metals/iron_sheet_metal_from_iron_block_stonecutting": {
    "criteria": {
      "has_iron_block": "2024-11-30 18:29:11 +0300"
    },
    "done": true
  },
  "mcwfences:recipes/birch": {
    "criteria": {
      "has_birch": "2024-11-29 21:36:38 +0300"
    },
    "done": true
  },
  "cfm:recipes/cfm/oak_table": {
    "criteria": {
      "has_planks": "2024-11-30 18:32:36 +0300"
    },
    "done": true
  },
  "smallships:recipes/transportation/jungle_galley": {
    "criteria": {
      "in_water": "2024-11-29 21:57:34 +0300"
    },
    "done": true
  },
  "minecraft:recipes/decorations/deepslate_tile_wall": {
    "criteria": {
      "has_deepslate_tiles": "2024-11-30 18:29:50 +0300"
    },
    "done": true
  },
  "minecraft:recipes/redstone/oak_pressure_plate": {
    "criteria": {
      "has_planks": "2024-11-30 18:32:36 +0300"
    },
    "done": true
  },
  "mcwwindows:recipes/shutters": {
    "criteria": {
      "has_wood": "2024-11-30 18:32:36 +0300"
    },
    "done": true
  },
  "smallships:recipes/transportation/acacia_brigg": {
    "criteria": {
      "in_water": "2024-11-29 21:57:35 +0300"
    },
    "done": true
  },
  "cfm:recipes/cfm/oak_bedside_cabinet": {
    "criteria": {
      "has_planks": "2024-11-30 18:32:36 +0300"
    },
    "done": true
  },
  "cfm:recipes/cfm/oak_kitchen_sink_dark": {
    "criteria": {
      "has_bottom": "2024-11-30 18:32:36 +0300"
    },
    "done": true
  },
  "cfm:recipes/cfm/oak_desk": {
    "criteria": {
      "has_planks": "2024-11-30 18:32:36 +0300"
    },
    "done": true
  },
  "mcwbridges:recipes/rope_oak_bridge": {
    "criteria": {
      "has_planks": "2024-11-30 18:32:36 +0300"
    },
    "done": true
  },
  "smallships:recipes/transportation/dark_oak_galley": {
    "criteria": {
      "in_water": "2024-11-29 21:57:35 +0300"
    },
    "done": true
  },
  "smallships:recipes/transportation/jungle_cog": {
    "criteria": {
      "in_water": "2024-11-29 21:57:35 +0300"
    },
    "done": true
  },
  "railways:recipes/railways_palettes/stonecutting/riveted_locometal": {
    "criteria": {
      "has_item": "2024-11-30 18:29:11 +0300"
    },
    "done": true
  },
  "minecraft:recipes/building_blocks/deepslate_tile_slab": {
    "criteria": {
      "has_deepslate_tiles": "2024-11-30 18:29:50 +0300"
    },
    "done": true
  },
  "minecraft:recipes/decorations/oak_sign": {
    "criteria": {
      "has_planks": "2024-11-30 18:32:36 +0300"
    },
    "done": true
  },
  "minecraft:recipes/redstone/oak_trapdoor": {
    "criteria": {
      "has_planks": "2024-11-30 18:32:36 +0300"
    },
    "done": true
  },
  "chiselsandbits:recipes/chiselsandbits/wrench": {
    "criteria": {
      "has_p": "2024-11-30 18:32:36 +0300"
    },
    "done": true
  },
  "mcwbridges:recipes/asian_red_bridge_pier": {
    "criteria": {
      "has_planks": "2024-11-30 18:32:36 +0300"
    },
    "done": true
  },
  "minecraft:recipes/redstone/oak_fence_gate": {
    "criteria": {
      "has_planks": "2024-11-30 18:32:36 +0300"
    },
    "done": true
  },
  "minecraft:recipes/redstone/oak_button": {
    "criteria": {
      "has_planks": "2024-11-30 18:32:36 +0300"
    },
    "done": true
  },
  "smallships:recipes/transportation/oak_brigg": {
    "criteria": {
      "in_water": "2024-11-29 21:57:35 +0300"
    },
    "done": true
  },
  "smallships:recipes/transportation/birch_galley": {
    "criteria": {
      "in_water": "2024-11-29 21:57:35 +0300"
    },
    "done": true
  },
  "cfm:recipes/cfm/oak_cabinet": {
    "criteria": {
      "has_planks": "2024-11-30 18:32:36 +0300"
    },
    "done": true
  },
  "mcwfences:recipes/blackstone": {
    "criteria": {
      "has_blackstone": "2024-11-29 21:36:38 +0300"
    },
    "done": true
  },
  "smallships:recipes/transportation/oak_drakkar": {
    "criteria": {
      "in_water": "2024-11-29 21:57:34 +0300"
    },
    "done": true
  },
  "minecraft:adventure/adventuring_time": {
    "criteria": {
      "minecraft:sunflower_plains": "2024-11-29 21:37:37 +0300",
      "minecraft:beach": "2024-11-30 18:58:13 +0300",
      "minecraft:river": "2024-11-29 21:37:34 +0300",
      "minecraft:stony_shore": "2024-11-30 18:44:41 +0300",
      "minecraft:forest": "2024-11-30 18:57:21 +0300",
      "minecraft:meadow": "2024-11-29 21:25:34 +0300",
      "minecraft:plains": "2024-11-29 21:31:04 +0300"
    },
    "done": false
  },
  "minecraft:recipes/building_blocks/deepslate_tile_stairs_from_deepslate_tiles_stonecutting": {
    "criteria": {
      "has_deepslate_tiles": "2024-11-30 18:29:50 +0300"
    },
    "done": true
  },
  "smallships:recipes/transportation/birch_brigg": {
    "criteria": {
      "in_water": "2024-11-29 21:57:34 +0300"
    },
    "done": true
  },
  "smallships:recipes/transportation/dark_oak_drakkar": {
    "criteria": {
      "in_water": "2024-11-29 21:57:35 +0300"
    },
    "done": true
  },
  "mcwbridges:recipes/oak_rail_bridge": {
    "criteria": {
      "has_planks": "2024-11-30 18:32:36 +0300"
    },
    "done": true
  },
  "mcwfences:recipes/nether": {
    "criteria": {
      "has_nether_brick": "2024-11-29 21:36:38 +0300"
    },
    "done": true
  },
  "minecraft:recipes/transportation/birch_boat": {
    "criteria": {
      "in_water": "2024-11-29 21:57:34 +0300"
    },
    "done": true
  },
  "design_decor:recipes/design_decor/wood_support_from_planks_stonecutting": {
    "criteria": {
      "has_planks": "2024-11-30 18:32:36 +0300"
    },
    "done": true
  },
  "minecraft:recipes/building_blocks/oak_stairs": {
    "criteria": {
      "has_planks": "2024-11-30 18:32:36 +0300"
    },
    "done": true
  },
  "cfm:recipes/cfm/oak_kitchen_drawer": {
    "criteria": {
      "has_planks": "2024-11-30 18:32:36 +0300"
    },
    "done": true
  },
  "minecraft:recipes/decorations/barrel": {
    "criteria": {
      "has_planks": "2024-11-30 18:32:36 +0300"
    },
    "done": true
  },
  "minecraft:recipes/transportation/acacia_boat": {
    "criteria": {
      "in_water": "2024-11-29 21:57:35 +0300"
    },
    "done": true
  },
  "mcwfences:recipes/crimson": {
    "criteria": {
      "has_crimson": "2024-11-29 21:36:38 +0300"
    },
    "done": true
  },
  "mcwbridges:recipes/deepslate_tile_bridge": {
    "criteria": {
      "has_planks": "2024-11-30 18:29:50 +0300"
    },
    "done": true
  },
  "cfm:recipes/cfm/oak_desk_cabinet": {
    "criteria": {
      "has_planks": "2024-11-30 18:32:36 +0300"
    },
    "done": true
  },
  "minecraft:recipes/redstone/oak_door": {
    "criteria": {
      "has_planks": "2024-11-30 18:32:36 +0300"
    },
    "done": true
  },
  "minecraft:recipes/decorations/deepslate_tile_wall_from_deepslate_tiles_stonecutting": {
    "criteria": {
      "has_deepslate_tiles": "2024-11-30 18:29:50 +0300"
    },
    "done": true
  },
  "minecraft:recipes/building_blocks/cracked_deepslate_tiles": {
    "criteria": {
      "has_deepslate_tiles": "2024-11-30 18:29:50 +0300"
    },
    "done": true
  },
  "minecraft:adventure/root": {
    "criteria": {
      "killed_by_something": "2024-11-29 21:34:03 +0300"
    },
    "done": true
  },
  "smallships:recipes/transportation/mangrove_galley": {
    "criteria": {
      "in_water": "2024-11-29 21:57:34 +0300"
    },
    "done": true
  },
  "smallships:recipes/misc/sail": {
    "criteria": {
      "in_water": "2024-11-29 21:57:35 +0300"
    },
    "done": true
  },
  "mcwfences:recipes/prismarine": {
    "criteria": {
      "has_qq": "2024-11-29 21:36:38 +0300"
    },
    "done": true
  },
  "mcwfences:recipes/bamboo": {
    "criteria": {
      "has_bamboo": "2024-11-29 21:36:38 +0300"
    },
    "done": true
  },
  "minecraft:recipes/transportation/jungle_boat": {
    "criteria": {
      "in_water": "2024-11-29 21:57:35 +0300"
    },
    "done": true
  },
  "mcwfences:recipes/acacia": {
    "criteria": {
      "has_acacia": "2024-11-29 21:36:38 +0300"
    },
    "done": true
  },
  "minecraft:recipes/misc/iron_ingot_from_iron_block": {
    "criteria": {
      "has_iron_block": "2024-11-30 18:29:10 +0300"
    },
    "done": true
  },
  "mcwwindows:recipes/parapets": {
    "criteria": {
      "has_wood": "2024-11-30 18:32:36 +0300"
    },
    "done": true
  },
  "chiselsandbits:recipes/chiselsandbits/modification_table": {
    "criteria": {
      "has_p": "2024-11-30 18:32:36 +0300"
    },
    "done": true
  },
  "minecraft:recipes/transportation/dark_oak_boat": {
    "criteria": {
      "in_water": "2024-11-29 21:57:34 +0300"
    },
    "done": true
  },
  "smallships:recipes/transportation/oak_galley": {
    "criteria": {
      "in_water": "2024-11-29 21:57:35 +0300"
    },
    "done": true
  },
  "mcwbridges:recipes/balustrade_deepslate_tiles_bridge": {
    "criteria": {
      "has_planks": "2024-11-30 18:29:50 +0300"
    },
    "done": true
  },
  "minecraft:recipes/building_blocks/deepslate_tile_slab_from_deepslate_tiles_stonecutting": {
    "criteria": {
      "has_deepslate_tiles": "2024-11-30 18:29:50 +0300"
    },
    "done": true
  },
  "mcwfences:recipes/quartz": {
    "criteria": {
      "has_qq": "2024-11-29 21:36:38 +0300"
    },
    "done": true
  },
  "smallships:recipes/transportation/mangrove_brigg": {
    "criteria": {
      "in_water": "2024-11-29 21:57:34 +0300"
    },
    "done": true
  },
  "smallships:recipes/transportation/spruce_galley": {
    "criteria": {
      "in_water": "2024-11-29 21:57:34 +0300"
    },
    "done": true
  },
  "smallships:recipes/transportation/acacia_drakkar": {
    "criteria": {
      "in_water": "2024-11-29 21:57:34 +0300"
    },
    "done": true
  },
  "smallships:recipes/transportation/spruce_brigg": {
    "criteria": {
      "in_water": "2024-11-29 21:57:34 +0300"
    },
    "done": true
  },
  "mcwfences:recipes/dark_oak": {
    "criteria": {
      "has_dark_oak": "2024-11-29 21:36:38 +0300"
    },
    "done": true
  },
  "smallships:recipes/transportation/jungle_brigg": {
    "criteria": {
      "in_water": "2024-11-29 21:57:35 +0300"
    },
    "done": true
  },
  "create:root": {
    "criteria": {
      "0": "2024-11-29 21:36:38 +0300"
    },
    "done": true
  },
  "smallships:recipes/transportation/dark_oak_brigg": {
    "criteria": {
      "in_water": "2024-11-29 21:57:34 +0300"
    },
    "done": true
  },
  "smallships:recipes/transportation/dark_oak_cog": {
    "criteria": {
      "in_water": "2024-11-29 21:57:34 +0300"
    },
    "done": true
  },
  "minecraft:recipes/decorations/oak_fence": {
    "criteria": {
      "has_planks": "2024-11-30 18:32:36 +0300"
    },
    "done": true
  },
  "minecraft:recipes/transportation/oak_boat": {
    "criteria": {
      "in_water": "2024-11-29 21:57:35 +0300"
    },
    "done": true
  },
  "smallships:recipes/transportation/spruce_cog": {
    "criteria": {
      "in_water": "2024-11-29 21:57:35 +0300"
    },
    "done": true
  },
  "minecraft:recipes/decorations/anvil": {
    "criteria": {
      "has_iron_block": "2024-11-30 18:29:11 +0300"
    },
    "done": true
  },
  "smallships:recipes/transportation/mangrove_drakkar": {
    "criteria": {
      "in_water": "2024-11-29 21:57:34 +0300"
    },
    "done": true
  },
  "minecraft:recipes/building_blocks/oak_slab": {
    "criteria": {
      "has_planks": "2024-11-30 18:32:36 +0300"
    },
    "done": true
  },
  "minecraft:recipes/building_blocks/deepslate_tile_stairs": {
    "criteria": {
      "has_deepslate_tiles": "2024-11-30 18:29:50 +0300"
    },
    "done": true
  },
  "cfm:recipes/cfm/oak_kitchen_sink_light": {
    "criteria": {
      "has_bottom": "2024-11-30 18:32:36 +0300"
    },
    "done": true
  },
  "mcwbridges:recipes/deepslate_tile_bridge_pier": {
    "criteria": {
      "has_planks": "2024-11-30 18:29:50 +0300"
    },
    "done": true
  },
  "cfm:recipes/cfm/oak_park_bench": {
    "criteria": {
      "has_planks": "2024-11-30 18:32:36 +0300"
    },
    "done": true
  },
  "cfm:recipes/cfm/oak_coffee_table": {
    "criteria": {
      "has_planks": "2024-11-30 18:32:36 +0300"
    },
    "done": true
  },
  "DataVersion": 3120
}